rabbitmq_utils/__init__.py
rabbitmq_utils/consumer.py
rabbitmq_utils/producer.py
rabbitmq_utils/rpc/__init__.py
rabbitmq_utils/rpc/client.py
rabbitmq_utils/rpc/server.py
rabbitmq_utils-1.5.0.dist-info/licenses/LICENSE
rabbitmq_utils-1.5.0.dist-info/METADATA
rabbitmq_utils-1.5.0.dist-info/WHEEL
rabbitmq_utils-1.5.0.dist-info/top_level.txt
rabbitmq_utils-1.5.0.dist-info/RECORD
