Metadata-Version: 2.4
Name: rabbitmq-utils
Version: 1.5.0
Summary: Provide easy connection to RabbitMQ server.
Author-email: Tahir Rafique <tahirrafiqueasad@gmail.com>
License-Expression: MIT
Keywords: rabbitmq,consumer,producer,publisher,subscriber
Classifier: Development Status :: 5 - Production/Stable
Classifier: Programming Language :: Python :: 3
Classifier: Programming Language :: Python :: 3.7
Classifier: Programming Language :: Python :: 3.8
Classifier: Operating System :: OS Independent
Classifier: Intended Audience :: Developers
Classifier: Intended Audience :: Science/Research
Classifier: Intended Audience :: Information Technology
Classifier: Natural Language :: English
Classifier: Topic :: Software Development :: Libraries :: Python Modules
Requires-Python: >=3.8
License-File: LICENSE
Requires-Dist: pika>=1.3.0
Dynamic: license-file
